mdplan/__init__.py
mdplan/__main__.py
mdplan/count.py
mdplan/parse.py
mdplan/task.py
mdplan/tree.py
mdplan/utils.py
mdplan/data/plot_template.html
mdplan/git/__init__.py
mdplan/git/history.py
mdplan/git/plot.py
mdplan/tests/__init__.py
mdplan/tests/fixtures.py
mdplan/tests/test_count.py
mdplan/tests/test_git.py
mdplan/tests/test_parse.py
mdplan/tests/test_plot.py
mdplan/tests/test_tree.py
markdown_plan-1.0.2.dist-info/METADATA
markdown_plan-1.0.2.dist-info/WHEEL
markdown_plan-1.0.2.dist-info/entry_points.txt
markdown_plan-1.0.2.dist-info/top_level.txt
markdown_plan-1.0.2.dist-info/RECORD
